{"Response":{"MetaInfo":{"Timestamp":"2020-03-28T09:43:01.027+0000","NextPageInformation":"2"},"View":[{"_type":"SearchResultsViewType","ViewId":0,"Result":[{"Relevance":1.0,"Distance":0.0,"Direction":0.0,"MatchLevel":"city","MatchQuality":{"Country":1.0,"State":1.0,"County":1.0,"City":1.0,"PostalCode":1.0},"Location":{"LocationId":"NT_yoVipy3PZQRAUtvsbsPgOB","LocationType":"point","DisplayPosition":{"Latitude":38.9698394,"Longitude":-0.1867794},"MapView":{"TopLeft":{"Latitude":39.04101,"Longitude":-0.29618},"BottomRight":{"Latitude":38.94979,"Longitude":-0.1443}},"Address":{"Label":"Gandia, Comunitat Valenciana, Espanya","Country":"ESP","State":"Comunitat Valenciana","County":"València","City":"Gandia","PostalCode":"46701","AdditionalData":[{"value":"Espanya","key":"CountryName"},{"value":"Comunitat Valenciana","key":"StateName"},{"value":"València","key":"CountyName"}]},"MapReference":{"ReferenceId":"1027780440","SideOfStreet":"neither","CountryId":"20215059","StateId":"20226784","CountyId":"20226787","CityId":"20250222"}}},{"Relevance":1.0,"Distance":11.8,"MatchLevel":"houseNumber","MatchQuality":{"Country":1.0,"State":1.0,"County":1.0,"City":1.0,"Street":[1.0],"HouseNumber":1.0,"PostalCode":1.0},"MatchType":"interpolated","Location":{"LocationId":"NT_LgBl-iwD6WpQuNvCRiFXaD_zMD","LocationType":"point","DisplayPosition":{"Latitude":38.96992,"Longitude":-0.1869},"MapView":{"TopLeft":{"Latitude":38.9710442,"Longitude":-0.1883459},"BottomRight":{"Latitude":38.9687958,"Longitude":-0.1854541}},"Address":{"Label":"Avenida Beniopa, 33, 46701 Gandia (Valencia), Espanya","Country":"ESP","State":"Comunidad Valenciana","County":"Valencia","City":"Gandia","Street":"Avenida Beniopa","HouseNumber":"33","PostalCode":"46701","AdditionalData":[{"value":"Espanya","key":"CountryName"},{"value":"Comunidad Valenciana","key":"StateName"},{"value":"Valencia","key":"CountyName"}]},"MapReference":{"ReferenceId":"576459868","Spot":0.62,"SideOfStreet":"left","CountryId":"20215059","StateId":"20226784","CountyId":"20226787","CityId":"20250222","AddressId":"269449673","RoadLinkId":"388047968"}}},{"Relevance":1.0,"Distance":25.7,"MatchLevel":"houseNumber","MatchQuality":{"Country":1.0,"State":1.0,"County":1.0,"City":1.0,"Street":[1.0],"HouseNumber":1.0,"PostalCode":1.0},"MatchType":"interpolated","Location":{"LocationId":"NT_TBziZeEEJ1WmC0uoXeuI0D_l_576459442_L_zMD","LocationType":"point","DisplayPosition":{"Latitude":38.9695525,"Longitude":-0.186559},"MapView":{"TopLeft":{"Latitude":38.9706766,"Longitude":-0.1880049},"BottomRight":{"Latitude":38.9684283,"Longitude":-0.1851131}},"Address":{"Label":"Calle Xeraco, 33, 46702 Gandia (Valencia), Espanya","Country":"ESP","State":"Comunidad Valenciana","County":"Valencia","City":"Gandia","Street":"Calle Xeraco","HouseNumber":"33","PostalCode":"46702","AdditionalData":[{"value":"Espanya","key":"CountryName"},{"value":"Comunidad Valenciana","key":"StateName"},{"value":"Valencia","key":"CountyName"}]},"MapReference":{"ReferenceId":"576459442","Spot":0.5,"SideOfStreet":"left","CountryId":"20215059","StateId":"20226784","CountyId":"20226787","CityId":"20250222"}}},{"Relevance":1.0,"Distance":36.8,"MatchLevel":"street","MatchQuality":{"Country":1.0,"State":1.0,"County":1.0,"City":1.0,"Street":[1.0],"PostalCode":1.0},"Location":{"LocationId":"NT_LgBl-iwD6WpQuNvCRiFXaD_l_1027776873_L","LocationType":"point","DisplayPosition":{"Latitude":38.96995,"Longitude":-0.18718},"MapView":{"TopLeft":{"Latitude":38.96999,"Longitude":-0.18745},"BottomRight":{"Latitude":38.96995,"Longitude":-0.18718}},"Address":{"Label":"Avenida Beniopa, 46701 Gandia (Valencia), Espanya","Country":"ESP","State":"Comunidad Valenciana","County":"Valencia","City":"Gandia","Street":"Avenida Beniopa","PostalCode":"46701","AdditionalData":[{"value":"Espanya","key":"CountryName"},{"value":"Comunidad Valenciana","key":"StateName"},{"value":"Valencia","key":"CountyName"}]},"MapReference":{"ReferenceId":"1027776873","Spot":0.0,"SideOfStreet":"left","CountryId":"20215059","StateId":"20226784","CountyId":"20226787","CityId":"20250222"}}},{"Relevance":1.0,"Distance":39.9,"MatchLevel":"houseNumber","MatchQuality":{"Country":1.0,"State":1.0,"County":1.0,"City":1.0,"Street":[1.0],"HouseNumber":1.0,"PostalCode":1.0},"MatchType":"interpolated","Location":{"LocationId":"NT_LgBl-iwD6WpQuNvCRiFXaD_ykD","LocationType":"point","DisplayPosition":{"Latitude":38.96987,"Longitude":-0.18631},"MapView":{"TopLeft":{"Latitude":38.9709942,"Longitude":-0.1877559},"BottomRight":{"Latitude":38.9687458,"Longitude":-0.1848641}},"Address":{"Label":"Avenida Beniopa, 29, 46701 Gandia (Valencia), Espanya","Country":"ESP","State":"Comunidad Valenciana","County":"Valencia","City":"Gandia","Street":"Avenida Beniopa","HouseNumber":"29","PostalCode":"46701","AdditionalData":[{"value":"Espanya","key":"CountryName"},{"value":"Comunidad Valenciana","key":"StateName"},{"value":"Valencia","key":"CountyName"}]},"MapReference":{"ReferenceId":"1027776872","Spot":0.62,"SideOfStreet":"left","CountryId":"20215059","StateId":"20226784","CountyId":"20226787","CityId":"20250222","AddressId":"269323984","RoadLinkId":"350459588"}}},{"Relevance":1.0,"Distance":44.4,"MatchLevel":"houseNumber","MatchQuality":{"Country":1.0,"State":1.0,"County":1.0,"City":1.0,"Street":[1.0],"HouseNumber":1.0,"PostalCode":1.0},"MatchType":"interpolated","Location":{"LocationId":"NT_LjRdWPCg-wlakHGvL5xl7A_l_576459937_R_1YD","LocationType":"point","DisplayPosition":{"Latitude":38.9696421,"Longitude":-0.1873117},"MapView":{"TopLeft":{"Latitude":38.9707663,"Longitude":-0.1887576},"BottomRight":{"Latitude":38.968518,"Longitude":-0.1858658}},"Address":{"Label":"Calle Primero de Mayo, 56, 46702 Gandia (Valencia), Espanya","Country":"ESP","State":"Comunidad Valenciana","County":"Valencia","City":"Gandia","Street":"Calle Primero de Mayo","HouseNumber":"56","PostalCode":"46702","AdditionalData":[{"value":"Espanya","key":"CountryName"},{"value":"Comunidad Valenciana","key":"StateName"},{"value":"Valencia","key":"CountyName"}]},"MapReference":{"ReferenceId":"576459937","Spot":0.51,"SideOfStreet":"right","CountryId":"20215059","StateId":"20226784","CountyId":"20226787","CityId":"20250222"}}},{"Relevance":1.0,"Distance":44.8,"MatchLevel":"houseNumber","MatchQuality":{"Country":1.0,"State":1.0,"County":1.0,"City":1.0,"Street":[1.0],"HouseNumber":1.0,"PostalCode":1.0},"MatchType":"interpolated","Location":{"LocationId":"NT_arw0QjzKVUFJuwF15aUi4C_0A","LocationType":"point","DisplayPosition":{"Latitude":38.97015,"Longitude":-0.18713},"MapView":{"TopLeft":{"Latitude":38.9712742,"Longitude":-0.1885759},"BottomRight":{"Latitude":38.9690258,"Longitude":-0.1856841}},"Address":{"Label":"Calle Montdúver, 4, 46701 Gandia (Valencia), Espanya","Country":"ESP","State":"Comunidad Valenciana","County":"Valencia","City":"Gandia","Street":"Calle Montdúver","HouseNumber":"4","PostalCode":"46701","AdditionalData":[{"value":"Espanya","key":"CountryName"},{"value":"Comunidad Valenciana","key":"StateName"},{"value":"Valencia","key":"CountyName"}]},"MapReference":{"ReferenceId":"576459649","Spot":0.17,"SideOfStreet":"right","CountryId":"20215059","StateId":"20226784","CountyId":"20226787","CityId":"20250222","AddressId":"269411747","RoadLinkId":"66452893"}}},{"Relevance":1.0,"Distance":54.8,"MatchLevel":"houseNumber","MatchQuality":{"Country":1.0,"State":1.0,"County":1.0,"City":1.0,"Street":[1.0],"HouseNumber":1.0,"PostalCode":1.0},"MatchType":"interpolated","Location":{"LocationId":"NT_L8PXXWI29WIsITfvTYqtVB_1ED","LocationType":"point","DisplayPosition":{"Latitude":38.96964,"Longitude":-0.18606},"MapView":{"TopLeft":{"Latitude":38.9707642,"Longitude":-0.1875059},"BottomRight":{"Latitude":38.9685158,"Longitude":-0.1846141}},"Address":{"Label":"Calle Abad Solá, 51, 46702 Gandia (Valencia), Espanya","Country":"ESP","State":"Comunidad Valenciana","County":"Valencia","City":"Gandia","Street":"Calle Abad Solá","HouseNumber":"51","PostalCode":"46702","AdditionalData":[{"value":"Espanya","key":"CountryName"},{"value":"Comunidad Valenciana","key":"StateName"},{"value":"Valencia","key":"CountyName"}]},"MapReference":{"ReferenceId":"576459557","Spot":0.7,"SideOfStreet":"left","CountryId":"20215059","StateId":"20226784","CountyId":"20226787","CityId":"20250222","AddressId":"269394302","RoadLinkId":"65441255"}}},{"Relevance":1.0,"Distance":58.7,"MatchLevel":"street","MatchQuality":{"Country":1.0,"State":1.0,"County":1.0,"City":1.0,"Street":[1.0],"PostalCode":1.0},"Location":{"LocationId":"NT_LgBl-iwD6WpQuNvCRiFXaD_l_1027776871_L","LocationType":"point","DisplayPosition":{"Latitude":38.96985,"Longitude":-0.1861},"MapView":{"TopLeft":{"Latitude":38.96985,"Longitude":-0.1861},"BottomRight":{"Latitude":38.96984,"Longitude":-0.18597}},"Address":{"Label":"Avenida Beniopa, 46701 Gandia (Valencia), Espanya","Country":"ESP","State":"Comunidad Valenciana","County":"Valencia","City":"Gandia","Street":"Avenida Beniopa","PostalCode":"46701","AdditionalData":[{"value":"Espanya","key":"CountryName"},{"value":"Comunidad Valenciana","key":"StateName"},{"value":"Valencia","key":"CountyName"}]},"MapReference":{"ReferenceId":"1027776871","Spot":1.0,"SideOfStreet":"left","CountryId":"20215059","StateId":"20226784","CountyId":"20226787","CityId":"20250222"}}},{"Relevance":1.0,"Distance":61.3,"MatchLevel":"houseNumber","MatchQuality":{"Country":1.0,"State":1.0,"County":1.0,"City":1.0,"Street":[1.0],"HouseNumber":1.0,"PostalCode":1.0},"MatchType":"interpolated","Location":{"LocationId":"NT_L1N0hpj5FMVjOzGxwts4dA_1MD","LocationType":"point","DisplayPosition":{"Latitude":38.96994,"Longitude":-0.18594},"MapView":{"TopLeft":{"Latitude":38.9710642,"Longitude":-0.1873859},"BottomRight":{"Latitude":38.9688158,"Longitude":-0.1844941}},"Address":{"Label":"Calle Abad Solá, 53, 46701 Gandia (Valencia), Espanya","Country":"ESP","State":"Comunidad Valenciana","County":"Valencia","City":"Gandia","Street":"Calle Abad Solá","HouseNumber":"53","PostalCode":"46701","AdditionalData":[{"value":"Espanya","key":"CountryName"},{"value":"Comunidad Valenciana","key":"StateName"},{"value":"Valencia","key":"CountyName"}]},"MapReference":{"ReferenceId":"576459983","Spot":0.08,"SideOfStreet":"left","CountryId":"20215059","StateId":"20226784","CountyId":"20226787","CityId":"20250222","AddressId":"269570028","RoadLinkId":"388047830"}}}]}]}}