{"Response":{"MetaInfo":{"Timestamp":"2020-03-28T10:59:45.927+0000","NextPageInformation":"2"},"View":[{"_type":"SearchResultsViewType","ViewId":0,"Result":[{"Relevance":1.0,"Distance":0.0,"Direction":0.0,"MatchLevel":"district","MatchQuality":{"Country":1.0,"State":1.0,"County":1.0,"City":1.0,"District":1.0,"PostalCode":1.0},"Location":{"LocationId":"NT_m1Tbvp-45lj0Dx1brHy4-B","LocationType":"point","DisplayPosition":{"Latitude":48.0169642,"Longitude":8.5420776},"MapView":{"TopLeft":{"Latitude":48.0385,"Longitude":8.52189},"BottomRight":{"Latitude":48.01054,"Longitude":8.55178}},"Address":{"Label":"Bad Dürrheim, Baden-Württemberg, Deutschland","Country":"DEU","State":"Baden-Württemberg","County":"Schwarzwald-Baar-Kreis","City":"Bad Dürrheim","District":"Bad Dürrheim","PostalCode":"78073","AdditionalData":[{"value":"Deutschland","key":"CountryName"},{"value":"Baden-Württemberg","key":"StateName"},{"value":"Schwarzwald-Baar-Kreis","key":"CountyName"}]},"MapReference":{"ReferenceId":"1246091281","SideOfStreet":"neither","CountryId":"20147700","StateId":"20171489","CountyId":"20175081","CityId":"20175082","DistrictId":"20175087"}}},{"Relevance":1.0,"Distance":4.4,"MatchLevel":"houseNumber","MatchQuality":{"Country":1.0,"State":1.0,"County":1.0,"City":1.0,"District":1.0,"Street":[1.0],"HouseNumber":1.0,"PostalCode":1.0},"MatchType":"interpolated","Location":{"LocationId":"NT_MOt9pLFt3hsB3HPJyGdRSB_xUD","LocationType":"point","DisplayPosition":{"Latitude":48.01708,"Longitude":8.54199},"MapView":{"TopLeft":{"Latitude":48.0182042,"Longitude":8.5403094},"BottomRight":{"Latitude":48.0159558,"Longitude":8.5436706}},"Address":{"Label":"Gartenstraße 15, 78073 Bad Dürrheim, Deutschland","Country":"DEU","State":"Baden-Württemberg","County":"Schwarzwald-Baar-Kreis","City":"Bad Dürrheim","District":"Bad Dürrheim","Street":"Gartenstraße","HouseNumber":"15","PostalCode":"78073","AdditionalData":[{"value":"Deutschland","key":"CountryName"},{"value":"Baden-Württemberg","key":"StateName"},{"value":"Schwarzwald-Baar-Kreis","key":"CountyName"}]},"MapReference":{"ReferenceId":"78635971","Spot":1.0,"SideOfStreet":"right","CountryId":"20147700","StateId":"20171489","CountyId":"20175081","CityId":"20175082","DistrictId":"20175087","AddressId":"414566507","RoadLinkId":"38141448"}}},{"Relevance":1.0,"Distance":47.8,"MatchLevel":"houseNumber","MatchQuality":{"Country":1.0,"State":1.0,"County":1.0,"City":1.0,"District":1.0,"Street":[1.0],"HouseNumber":1.0,"PostalCode":1.0},"MatchType":"interpolated","Location":{"LocationId":"NT_SE1HJy8e.Tgu1wX4QSbbfD_yUD","LocationType":"point","DisplayPosition":{"Latitude":48.01753,"Longitude":8.542},"MapView":{"TopLeft":{"Latitude":48.0186542,"Longitude":8.5403194},"BottomRight":{"Latitude":48.0164058,"Longitude":8.5436806}},"Address":{"Label":"Waldstraße 25, 78073 Bad Dürrheim, Deutschland","Country":"DEU","State":"Baden-Württemberg","County":"Schwarzwald-Baar-Kreis","City":"Bad Dürrheim","District":"Bad Dürrheim","Street":"Waldstraße","HouseNumber":"25","PostalCode":"78073","AdditionalData":[{"value":"Deutschland","key":"CountryName"},{"value":"Baden-Württemberg","key":"StateName"},{"value":"Schwarzwald-Baar-Kreis","key":"CountyName"}]},"MapReference":{"ReferenceId":"589238544","Spot":0.1,"SideOfStreet":"left","CountryId":"20147700","StateId":"20171489","CountyId":"20175081","CityId":"20175082","DistrictId":"20175087","AddressId":"180250252","RoadLinkId":"38130992"}}},{"Relevance":1.0,"Distance":88.7,"MatchLevel":"houseNumber","MatchQuality":{"Country":1.0,"State":1.0,"County":1.0,"City":1.0,"District":1.0,"Street":[1.0],"HouseNumber":1.0,"PostalCode":1.0},"MatchType":"interpolated","Location":{"LocationId":"NT_QxmjiiYDpVX1A1HGq-gWXC_yA","LocationType":"point","DisplayPosition":{"Latitude":48.01781,"Longitude":8.54206},"MapView":{"TopLeft":{"Latitude":48.0189342,"Longitude":8.5403794},"BottomRight":{"Latitude":48.0166858,"Longitude":8.5437406}},"Address":{"Label":"Sonnenstraße 2, 78073 Bad Dürrheim, Deutschland","Country":"DEU","State":"Baden-Württemberg","County":"Schwarzwald-Baar-Kreis","City":"Bad Dürrheim","District":"Bad Dürrheim","Street":"Sonnenstraße","HouseNumber":"2","PostalCode":"78073","AdditionalData":[{"value":"Deutschland","key":"CountryName"},{"value":"Baden-Württemberg","key":"StateName"},{"value":"Schwarzwald-Baar-Kreis","key":"CountyName"}]},"MapReference":{"ReferenceId":"589238545","Spot":0.12,"SideOfStreet":"left","CountryId":"20147700","StateId":"20171489","CountyId":"20175081","CityId":"20175082","DistrictId":"20175087","AddressId":"177367953","RoadLinkId":"38086242"}}},{"Relevance":1.0,"Distance":152.4,"MatchLevel":"houseNumber","MatchQuality":{"Country":1.0,"State":1.0,"County":1.0,"City":1.0,"District":1.0,"Street":[1.0],"HouseNumber":1.0,"PostalCode":1.0},"MatchType":"interpolated","Location":{"LocationId":"NT_SE1HJy8e.Tgu1wX4QSbbfD_xcD","LocationType":"point","DisplayPosition":{"Latitude":48.01775,"Longitude":8.54019},"MapView":{"TopLeft":{"Latitude":48.0188742,"Longitude":8.5385094},"BottomRight":{"Latitude":48.0166258,"Longitude":8.5418706}},"Address":{"Label":"Waldstraße 17, 78073 Bad Dürrheim, Deutschland","Country":"DEU","State":"Baden-Württemberg","County":"Schwarzwald-Baar-Kreis","City":"Bad Dürrheim","District":"Bad Dürrheim","Street":"Waldstraße","HouseNumber":"17","PostalCode":"78073","AdditionalData":[{"value":"Deutschland","key":"CountryName"},{"value":"Baden-Württemberg","key":"StateName"},{"value":"Schwarzwald-Baar-Kreis","key":"CountyName"}]},"MapReference":{"ReferenceId":"78635961","Spot":0.82,"SideOfStreet":"right","CountryId":"20147700","StateId":"20171489","CountyId":"20175081","CityId":"20175082","DistrictId":"20175087","AddressId":"180454606","RoadLinkId":"38126582"}}},{"Relevance":1.0,"Distance":174.7,"MatchLevel":"houseNumber","MatchQuality":{"Country":1.0,"State":1.0,"County":1.0,"City":1.0,"District":1.0,"Street":[1.0],"HouseNumber":1.0,"PostalCode":1.0},"MatchType":"interpolated","Location":{"LocationId":"NT_C7UUJG3vzMemDoJNlBSo1B_2A","LocationType":"point","DisplayPosition":{"Latitude":48.01832,"Longitude":8.54054},"MapView":{"TopLeft":{"Latitude":48.0194442,"Longitude":8.5388594},"BottomRight":{"Latitude":48.0171958,"Longitude":8.5422206}},"Address":{"Label":"Ahornweg 6, 78073 Bad Dürrheim, Deutschland","Country":"DEU","State":"Baden-Württemberg","County":"Schwarzwald-Baar-Kreis","City":"Bad Dürrheim","District":"Bad Dürrheim","Street":"Ahornweg","HouseNumber":"6","PostalCode":"78073","AdditionalData":[{"value":"Deutschland","key":"CountryName"},{"value":"Baden-Württemberg","key":"StateName"},{"value":"Schwarzwald-Baar-Kreis","key":"CountyName"}]},"MapReference":{"ReferenceId":"78635960","Spot":0.44,"SideOfStreet":"right","CountryId":"20147700","StateId":"20171489","CountyId":"20175081","CityId":"20175082","DistrictId":"20175087","AddressId":"179637603","RoadLinkId":"38361705"}}},{"Relevance":1.0,"Distance":189.6,"MatchLevel":"houseNumber","MatchQuality":{"Country":1.0,"State":1.0,"County":1.0,"City":1.0,"District":1.0,"Street":[1.0],"HouseNumber":1.0,"PostalCode":1.0},"MatchType":"interpolated","Location":{"LocationId":"NT_fOTuobFq0KqrLOzIKk3iZB_2A","LocationType":"point","DisplayPosition":{"Latitude":48.01854,"Longitude":8.54305},"MapView":{"TopLeft":{"Latitude":48.0196642,"Longitude":8.5413694},"BottomRight":{"Latitude":48.0174158,"Longitude":8.5447306}},"Address":{"Label":"An der Sonnenhalde 6, 78073 Bad Dürrheim, Deutschland","Country":"DEU","State":"Baden-Württemberg","County":"Schwarzwald-Baar-Kreis","City":"Bad Dürrheim","District":"Bad Dürrheim","Street":"An der Sonnenhalde","HouseNumber":"6","PostalCode":"78073","AdditionalData":[{"value":"Deutschland","key":"CountryName"},{"value":"Baden-Württemberg","key":"StateName"},{"value":"Schwarzwald-Baar-Kreis","key":"CountyName"}]},"MapReference":{"ReferenceId":"78635958","Spot":0.0,"SideOfStreet":"right","CountryId":"20147700","StateId":"20171489","CountyId":"20175081","CityId":"20175082","DistrictId":"20175087","AddressId":"249660942","RoadLinkId":"38473645"}}},{"Relevance":1.0,"Distance":195.4,"MatchLevel":"houseNumber","MatchQuality":{"Country":1.0,"State":1.0,"County":1.0,"City":1.0,"District":1.0,"Street":[1.0],"HouseNumber":1.0,"PostalCode":1.0},"MatchType":"interpolated","Location":{"LocationId":"NT_BmGN8gXjp11oqxFwpDPAwC_3A","LocationType":"point","DisplayPosition":{"Latitude":48.01524,"Longitude":8.54157},"MapView":{"TopLeft":{"Latitude":48.0163642,"Longitude":8.5398895},"BottomRight":{"Latitude":48.0141158,"Longitude":8.5432505}},"Address":{"Label":"Am Sonnenbühl 7, 78073 Bad Dürrheim, Deutschland","Country":"DEU","State":"Baden-Württemberg","County":"Schwarzwald-Baar-Kreis","City":"Bad Dürrheim","District":"Bad Dürrheim","Street":"Am Sonnenbühl","HouseNumber":"7","PostalCode":"78073","AdditionalData":[{"value":"Deutschland","key":"CountryName"},{"value":"Baden-Württemberg","key":"StateName"},{"value":"Schwarzwald-Baar-Kreis","key":"CountyName"}]},"MapReference":{"ReferenceId":"78635973","Spot":0.37,"SideOfStreet":"left","CountryId":"20147700","StateId":"20171489","CountyId":"20175081","CityId":"20175082","DistrictId":"20175087","AddressId":"179044466","RoadLinkId":"38378997"}}},{"Relevance":1.0,"Distance":195.8,"MatchLevel":"houseNumber","MatchQuality":{"Country":1.0,"State":1.0,"County":1.0,"City":1.0,"District":1.0,"Street":[1.0],"HouseNumber":1.0,"PostalCode":1.0},"MatchType":"interpolated","Location":{"LocationId":"NT_SE1HJy8e.Tgu1wX4QSbbfD_xMzLxA","LocationType":"point","DisplayPosition":{"Latitude":48.01741,"Longitude":8.53791},"MapView":{"TopLeft":{"Latitude":48.0185342,"Longitude":8.5362294},"BottomRight":{"Latitude":48.0162858,"Longitude":8.5395906}},"Address":{"Label":"Waldstraße 13/1, 78073 Bad Dürrheim, Deutschland","Country":"DEU","State":"Baden-Württemberg","County":"Schwarzwald-Baar-Kreis","City":"Bad Dürrheim","District":"Bad Dürrheim","Street":"Waldstraße","HouseNumber":"13/1","PostalCode":"78073","AdditionalData":[{"value":"Deutschland","key":"CountryName"},{"value":"Baden-Württemberg","key":"StateName"},{"value":"Schwarzwald-Baar-Kreis","key":"CountyName"}]},"MapReference":{"ReferenceId":"78635970","Spot":0.5,"SideOfStreet":"right","CountryId":"20147700","StateId":"20171489","CountyId":"20175081","CityId":"20175082","DistrictId":"20175087","AddressId":"177409135","RoadLinkId":"38407735"}}},{"Relevance":1.0,"Distance":224.7,"MatchLevel":"houseNumber","MatchQuality":{"Country":1.0,"State":1.0,"County":1.0,"City":1.0,"District":1.0,"Street":[1.0],"HouseNumber":1.0,"PostalCode":1.0},"MatchType":"interpolated","Location":{"LocationId":"NT_A7gHIqOBvD6i8n1eoS.jED_0AzLxA","LocationType":"point","DisplayPosition":{"Latitude":48.01516,"Longitude":8.54002},"MapView":{"TopLeft":{"Latitude":48.0162842,"Longitude":8.5383395},"BottomRight":{"Latitude":48.0140358,"Longitude":8.5417005}},"Address":{"Label":"Luisenstraße 40/1, 78073 Bad Dürrheim, Deutschland","Country":"DEU","State":"Baden-Württemberg","County":"Schwarzwald-Baar-Kreis","City":"Bad Dürrheim","District":"Bad Dürrheim","Street":"Luisenstraße","HouseNumber":"40/1","PostalCode":"78073","AdditionalData":[{"value":"Deutschland","key":"CountryName"},{"value":"Baden-Württemberg","key":"StateName"},{"value":"Schwarzwald-Baar-Kreis","key":"CountyName"}]},"MapReference":{"ReferenceId":"1247151912","Spot":0.17,"SideOfStreet":"right","CountryId":"20147700","StateId":"20171489","CountyId":"20175081","CityId":"20175082","DistrictId":"20175087","AddressId":"178022279","RoadLinkId":"568885483"}}}]}]}}