{"Response":{"MetaInfo":{"Timestamp":"2020-03-28T11:42:46.135+0000","NextPageInformation":"2"},"View":[{"_type":"SearchResultsViewType","ViewId":0,"Result":[{"Relevance":1.0,"Distance":0.0,"Direction":0.0,"MatchLevel":"district","MatchQuality":{"Country":1.0,"State":1.0,"County":1.0,"City":1.0,"District":1.0,"PostalCode":1.0},"Location":{"LocationId":"NT_VH-hUeb8MrXdh1k4Lh9IRA","LocationType":"point","DisplayPosition":{"Latitude":49.0385218,"Longitude":10.9761117},"MapView":{"TopLeft":{"Latitude":49.04389,"Longitude":10.9465},"BottomRight":{"Latitude":49.00103,"Longitude":10.99685}},"Address":{"Label":"Weißenburg in Bayern, Bayern, Deutschland","Country":"DEU","State":"Bayern","County":"Weißenburg-Gunzenhausen","City":"Weißenburg in Bayern","District":"Weißenburg in Bayern","PostalCode":"91781","AdditionalData":[{"value":"Deutschland","key":"CountryName"},{"value":"Bayern","key":"StateName"},{"value":"Weißenburg-Gunzenhausen","key":"CountyName"}]},"MapReference":{"ReferenceId":"576315463","SideOfStreet":"neither","CountryId":"20147700","StateId":"20177250","CountyId":"20183802","CityId":"20183909","DistrictId":"20183911"}}},{"Relevance":1.0,"Distance":9.1,"MatchLevel":"houseNumber","MatchQuality":{"Country":1.0,"State":1.0,"County":1.0,"City":1.0,"District":1.0,"Street":[1.0],"HouseNumber":1.0,"PostalCode":1.0},"MatchType":"interpolated","Location":{"LocationId":"NT_QLsbb-jPmwqJLI34XIy-OA_0MD","LocationType":"point","DisplayPosition":{"Latitude":49.03833,"Longitude":10.97587},"MapView":{"TopLeft":{"Latitude":49.0394542,"Longitude":10.9741552},"BottomRight":{"Latitude":49.0372058,"Longitude":10.9775848}},"Address":{"Label":"Rothenburger Straße 43, 91781 Weißenburg in Bayern, Deutschland","Country":"DEU","State":"Bayern","County":"Weißenburg-Gunzenhausen","City":"Weißenburg in Bayern","District":"Weißenburg in Bayern","Street":"Rothenburger Straße","HouseNumber":"43","PostalCode":"91781","AdditionalData":[{"value":"Deutschland","key":"CountryName"},{"value":"Bayern","key":"StateName"},{"value":"Weißenburg-Gunzenhausen","key":"CountyName"}]},"MapReference":{"ReferenceId":"1261715558","Spot":0.35,"SideOfStreet":"right","CountryId":"20147700","StateId":"20177250","CountyId":"20183802","CityId":"20183909","DistrictId":"20183911","AddressId":"181985096","RoadLinkId":"587286826"}}},{"Relevance":1.0,"Distance":10.9,"MatchLevel":"street","MatchQuality":{"Country":1.0,"State":1.0,"County":1.0,"City":1.0,"District":1.0,"PostalCode":1.0},"Location":{"LocationId":"NT_FrN06Ss1XXppfjPljBXVRA_l_1261715559_L","LocationType":"point","DisplayPosition":{"Latitude":49.0384689,"Longitude":10.9762374},"MapView":{"TopLeft":{"Latitude":49.03857,"Longitude":10.9761},"BottomRight":{"Latitude":49.03821,"Longitude":10.97628}},"Address":{"Label":"91781 Weißenburg in Bayern, Deutschland","Country":"DEU","State":"Bayern","County":"Weißenburg-Gunzenhausen","City":"Weißenburg in Bayern","District":"Weißenburg in Bayern","PostalCode":"91781","AdditionalData":[{"value":"Deutschland","key":"CountryName"},{"value":"Bayern","key":"StateName"},{"value":"Weißenburg-Gunzenhausen","key":"CountyName"}]},"MapReference":{"ReferenceId":"1261715559","Spot":0.73,"SideOfStreet":"left","CountryId":"20147700","StateId":"20177250","CountyId":"20183802","CityId":"20183909","DistrictId":"20183911"}}},{"Relevance":1.0,"Distance":13.4,"MatchLevel":"street","MatchQuality":{"Country":1.0,"State":1.0,"County":1.0,"City":1.0,"District":1.0,"PostalCode":1.0},"Location":{"LocationId":"NT_FrN06Ss1XXppfjPljBXVRA_l_1189449721_L","LocationType":"point","DisplayPosition":{"Latitude":49.03857,"Longitude":10.97628},"MapView":{"TopLeft":{"Latitude":49.03885,"Longitude":10.97628},"BottomRight":{"Latitude":49.03857,"Longitude":10.97719}},"Address":{"Label":"91781 Weißenburg in Bayern, Deutschland","Country":"DEU","State":"Bayern","County":"Weißenburg-Gunzenhausen","City":"Weißenburg in Bayern","District":"Weißenburg in Bayern","PostalCode":"91781","AdditionalData":[{"value":"Deutschland","key":"CountryName"},{"value":"Bayern","key":"StateName"},{"value":"Weißenburg-Gunzenhausen","key":"CountyName"}]},"MapReference":{"ReferenceId":"1189449721","Spot":0.0,"SideOfStreet":"left","CountryId":"20147700","StateId":"20177250","CountyId":"20183802","CityId":"20183909","DistrictId":"20183911"}}},{"Relevance":1.0,"Distance":38.0,"MatchLevel":"houseNumber","MatchQuality":{"Country":1.0,"State":1.0,"County":1.0,"City":1.0,"District":1.0,"Street":[1.0],"HouseNumber":1.0,"PostalCode":1.0},"MatchType":"interpolated","Location":{"LocationId":"NT_QLsbb-jPmwqJLI34XIy-OA_0UD","LocationType":"point","DisplayPosition":{"Latitude":49.03818,"Longitude":10.97613},"MapView":{"TopLeft":{"Latitude":49.0393042,"Longitude":10.9744152},"BottomRight":{"Latitude":49.0370558,"Longitude":10.9778448}},"Address":{"Label":"Rothenburger Straße 45, 91781 Weißenburg in Bayern, Deutschland","Country":"DEU","State":"Bayern","County":"Weißenburg-Gunzenhausen","City":"Weißenburg in Bayern","District":"Weißenburg in Bayern","Street":"Rothenburger Straße","HouseNumber":"45","PostalCode":"91781","AdditionalData":[{"value":"Deutschland","key":"CountryName"},{"value":"Bayern","key":"StateName"},{"value":"Weißenburg-Gunzenhausen","key":"CountyName"}]},"MapReference":{"ReferenceId":"1261715557","Spot":0.96,"SideOfStreet":"right","CountryId":"20147700","StateId":"20177250","CountyId":"20183802","CityId":"20183909","DistrictId":"20183911","AddressId":"185478302","RoadLinkId":"587286825"}}},{"Relevance":1.0,"Distance":44.6,"MatchLevel":"houseNumber","MatchQuality":{"Country":1.0,"State":1.0,"County":1.0,"City":1.0,"District":1.0,"Street":[1.0],"HouseNumber":1.0,"PostalCode":1.0},"MatchType":"interpolated","Location":{"LocationId":"NT_QLsbb-jPmwqJLI34XIy-OA_zMD","LocationType":"point","DisplayPosition":{"Latitude":49.03878,"Longitude":10.97553},"MapView":{"TopLeft":{"Latitude":49.0399042,"Longitude":10.9738152},"BottomRight":{"Latitude":49.0376558,"Longitude":10.9772448}},"Address":{"Label":"Rothenburger Straße 33, 91781 Weißenburg in Bayern, Deutschland","Country":"DEU","State":"Bayern","County":"Weißenburg-Gunzenhausen","City":"Weißenburg in Bayern","District":"Weißenburg in Bayern","Street":"Rothenburger Straße","HouseNumber":"33","PostalCode":"91781","AdditionalData":[{"value":"Deutschland","key":"CountryName"},{"value":"Bayern","key":"StateName"},{"value":"Weißenburg-Gunzenhausen","key":"CountyName"}]},"MapReference":{"ReferenceId":"547349223","Spot":0.42,"SideOfStreet":"right","CountryId":"20147700","StateId":"20177250","CountyId":"20183802","CityId":"20183909","DistrictId":"20183911","AddressId":"186056285","RoadLinkId":"33785108"}}},{"Relevance":1.0,"Distance":63.4,"MatchLevel":"houseNumber","MatchQuality":{"Country":1.0,"State":1.0,"County":1.0,"City":1.0,"District":1.0,"Street":[1.0],"HouseNumber":1.0,"PostalCode":1.0},"MatchType":"interpolated","Location":{"LocationId":"NT_JeSALFnrHkYRp-jpP8FM0D_yYD","LocationType":"point","DisplayPosition":{"Latitude":49.03819,"Longitude":10.97712},"MapView":{"TopLeft":{"Latitude":49.0393142,"Longitude":10.9754052},"BottomRight":{"Latitude":49.0370658,"Longitude":10.9788348}},"Address":{"Label":"Lindenstraße 26, 91781 Weißenburg in Bayern, Deutschland","Country":"DEU","State":"Bayern","County":"Weißenburg-Gunzenhausen","City":"Weißenburg in Bayern","District":"Weißenburg in Bayern","Street":"Lindenstraße","HouseNumber":"26","PostalCode":"91781","AdditionalData":[{"value":"Deutschland","key":"CountryName"},{"value":"Bayern","key":"StateName"},{"value":"Weißenburg-Gunzenhausen","key":"CountyName"}]},"MapReference":{"ReferenceId":"542151453","Spot":0.09,"SideOfStreet":"left","CountryId":"20147700","StateId":"20177250","CountyId":"20183802","CityId":"20183909","DistrictId":"20183911","AddressId":"183506344","RoadLinkId":"33740912"}}},{"Relevance":1.0,"Distance":65.3,"MatchLevel":"houseNumber","MatchQuality":{"Country":1.0,"State":1.0,"County":1.0,"City":1.0,"District":1.0,"Street":[1.0],"HouseNumber":1.0,"PostalCode":1.0},"MatchType":"interpolated","Location":{"LocationId":"NT_JeSALFnrHkYRp-jpP8FM0D_yQD","LocationType":"point","DisplayPosition":{"Latitude":49.039,"Longitude":10.97721},"MapView":{"TopLeft":{"Latitude":49.0401242,"Longitude":10.9754952},"BottomRight":{"Latitude":49.0378758,"Longitude":10.9789248}},"Address":{"Label":"Lindenstraße 24, 91781 Weißenburg in Bayern, Deutschland","Country":"DEU","State":"Bayern","County":"Weißenburg-Gunzenhausen","City":"Weißenburg in Bayern","District":"Weißenburg in Bayern","Street":"Lindenstraße","HouseNumber":"24","PostalCode":"91781","AdditionalData":[{"value":"Deutschland","key":"CountryName"},{"value":"Bayern","key":"StateName"},{"value":"Weißenburg-Gunzenhausen","key":"CountyName"}]},"MapReference":{"ReferenceId":"1189449723","Spot":0.3,"SideOfStreet":"left","CountryId":"20147700","StateId":"20177250","CountyId":"20183802","CityId":"20183909","DistrictId":"20183911","AddressId":"185963565","RoadLinkId":"498582655"}}},{"Relevance":1.0,"Distance":67.9,"MatchLevel":"houseNumber","MatchQuality":{"Country":1.0,"State":1.0,"County":1.0,"City":1.0,"District":1.0,"Street":[1.0],"HouseNumber":1.0,"PostalCode":1.0},"MatchType":"interpolated","Location":{"LocationId":"NT_NN.c8to2LAxsV0thIE2qJD_zcD","LocationType":"point","DisplayPosition":{"Latitude":49.03819,"Longitude":10.97533},"MapView":{"TopLeft":{"Latitude":49.0393142,"Longitude":10.9736152},"BottomRight":{"Latitude":49.0370658,"Longitude":10.9770448}},"Address":{"Label":"Feuchtwanger Straße 37, 91781 Weißenburg in Bayern, Deutschland","Country":"DEU","State":"Bayern","County":"Weißenburg-Gunzenhausen","City":"Weißenburg in Bayern","District":"Weißenburg in Bayern","Street":"Feuchtwanger Straße","HouseNumber":"37","PostalCode":"91781","AdditionalData":[{"value":"Deutschland","key":"CountryName"},{"value":"Bayern","key":"StateName"},{"value":"Weißenburg-Gunzenhausen","key":"CountyName"}]},"MapReference":{"ReferenceId":"547349222","Spot":0.64,"SideOfStreet":"left","CountryId":"20147700","StateId":"20177250","CountyId":"20183802","CityId":"20183909","DistrictId":"20183911","AddressId":"832726113","RoadLinkId":"33509420"}}},{"Relevance":1.0,"Distance":73.6,"MatchLevel":"houseNumber","MatchQuality":{"Country":1.0,"State":1.0,"County":1.0,"City":1.0,"District":1.0,"Street":[1.0],"HouseNumber":1.0,"PostalCode":1.0},"MatchType":"interpolated","Location":{"LocationId":"NT_JeSALFnrHkYRp-jpP8FM0D_ygD","LocationType":"point","DisplayPosition":{"Latitude":49.03801,"Longitude":10.97708},"MapView":{"TopLeft":{"Latitude":49.0391342,"Longitude":10.9753652},"BottomRight":{"Latitude":49.0368858,"Longitude":10.9787948}},"Address":{"Label":"Lindenstraße 28, 91781 Weißenburg in Bayern, Deutschland","Country":"DEU","State":"Bayern","County":"Weißenburg-Gunzenhausen","City":"Weißenburg in Bayern","District":"Weißenburg in Bayern","Street":"Lindenstraße","HouseNumber":"28","PostalCode":"91781","AdditionalData":[{"value":"Deutschland","key":"CountryName"},{"value":"Bayern","key":"StateName"},{"value":"Weißenburg-Gunzenhausen","key":"CountyName"}]},"MapReference":{"ReferenceId":"542151508","Spot":0.76,"SideOfStreet":"left","CountryId":"20147700","StateId":"20177250","CountyId":"20183802","CityId":"20183909","DistrictId":"20183911","AddressId":"182933006","RoadLinkId":"32561908"}}}]}]}}