{"Response":{"MetaInfo":{"Timestamp":"2020-03-28T11:12:24.882+0000","NextPageInformation":"2"},"View":[{"_type":"SearchResultsViewType","ViewId":0,"Result":[{"Relevance":1.0,"Distance":-135.4,"MatchLevel":"landmark","MatchQuality":{"Country":1.0,"State":1.0,"Name":1.0},"Location":{"LocationId":"NT_6su2l00beSlXwUlYRySHIB","LocationType":"park","Name":"P.N.R. Boucles de la Seine Normande","DisplayPosition":{"Latitude":49.47633,"Longitude":0.77841},"MapView":{"TopLeft":{"Latitude":49.63447,"Longitude":0.30373},"BottomRight":{"Latitude":49.31818,"Longitude":1.05186}},"Address":{"Label":"France","Country":"FRA","State":"Normandie","AdditionalData":[{"value":"France","key":"CountryName"},{"value":"Normandie","key":"StateName"}]},"MapReference":{"CountryId":"20000001","StateId":"20057204","PlaceId":"1512262610"}}},{"Relevance":1.0,"Distance":0.0,"Direction":0.0,"MatchLevel":"city","MatchQuality":{"Country":1.0,"State":1.0,"County":1.0,"City":1.0,"PostalCode":1.0},"Location":{"LocationId":"NT_JhLCJZjDrLlmpDeOB3oKRB","LocationType":"point","DisplayPosition":{"Latitude":49.618243,"Longitude":0.7434611},"MapView":{"TopLeft":{"Latitude":49.63447,"Longitude":0.73682},"BottomRight":{"Latitude":49.60213,"Longitude":0.8005}},"Address":{"Label":"Yvetot, Normandie, France","Country":"FRA","State":"Normandie","County":"Seine-Maritime","City":"Yvetot","PostalCode":"76190","AdditionalData":[{"value":"France","key":"CountryName"},{"value":"Normandie","key":"StateName"},{"value":"Seine-Maritime","key":"CountyName"}]},"MapReference":{"ReferenceId":"545575814","SideOfStreet":"neither","CountryId":"20000001","StateId":"20057204","CountyId":"20038936","CityId":"20080039"}}},{"Relevance":1.0,"Distance":9.8,"MatchLevel":"street","MatchQuality":{"Country":1.0,"State":1.0,"County":1.0,"City":1.0,"Street":[1.0],"PostalCode":1.0},"Location":{"LocationId":"NT_9.mW5TOBJD3wwzR0ZMAC1D_l_1221784162_L","LocationType":"point","DisplayPosition":{"Latitude":49.618155,"Longitude":0.7434699},"MapView":{"TopLeft":{"Latitude":49.61817,"Longitude":0.74342},"BottomRight":{"Latitude":49.61815,"Longitude":0.74362}},"Address":{"Label":"Avenue du Maréchal Foch, 76190 Yvetot, France","Country":"FRA","State":"Normandie","County":"Seine-Maritime","City":"Yvetot","Street":"Avenue du Maréchal Foch","PostalCode":"76190","AdditionalData":[{"value":"France","key":"CountryName"},{"value":"Normandie","key":"StateName"},{"value":"Seine-Maritime","key":"CountyName"}]},"MapReference":{"ReferenceId":"1221784162","Spot":0.25,"SideOfStreet":"left","CountryId":"20000001","StateId":"20057204","CountyId":"20038936","CityId":"20080039"}}},{"Relevance":1.0,"Distance":16.3,"MatchLevel":"houseNumber","MatchQuality":{"Country":1.0,"State":1.0,"County":1.0,"City":1.0,"Street":[1.0],"HouseNumber":1.0,"PostalCode":1.0},"MatchType":"interpolated","Location":{"LocationId":"NT_9.mW5TOBJD3wwzR0ZMAC1D_1UD","LocationType":"point","DisplayPosition":{"Latitude":49.61814,"Longitude":0.7433},"MapView":{"TopLeft":{"Latitude":49.6192642,"Longitude":0.7415649},"BottomRight":{"Latitude":49.6170158,"Longitude":0.7450351}},"Address":{"Label":"55 Avenue du Maréchal Foch, 76190 Yvetot, France","Country":"FRA","State":"Normandie","County":"Seine-Maritime","City":"Yvetot","Street":"Avenue du Maréchal Foch","HouseNumber":"55","PostalCode":"76190","AdditionalData":[{"value":"France","key":"CountryName"},{"value":"Normandie","key":"StateName"},{"value":"Seine-Maritime","key":"CountyName"}]},"MapReference":{"ReferenceId":"1221762342","Spot":0.73,"SideOfStreet":"right","CountryId":"20000001","StateId":"20057204","CountyId":"20038936","CityId":"20080039","AddressId":"571105732","RoadLinkId":"539240031"}}},{"Relevance":1.0,"Distance":16.5,"MatchLevel":"houseNumber","MatchQuality":{"Country":1.0,"State":1.0,"County":1.0,"City":1.0,"Street":[1.0],"HouseNumber":1.0,"PostalCode":1.0},"MatchType":"interpolated","Location":{"LocationId":"NT_9.mW5TOBJD3wwzR0ZMAC1D_1MD","LocationType":"point","DisplayPosition":{"Latitude":49.61817,"Longitude":0.74366},"MapView":{"TopLeft":{"Latitude":49.6192942,"Longitude":0.7419249},"BottomRight":{"Latitude":49.6170458,"Longitude":0.7453951}},"Address":{"Label":"53 Avenue du Maréchal Foch, 76190 Yvetot, France","Country":"FRA","State":"Normandie","County":"Seine-Maritime","City":"Yvetot","Street":"Avenue du Maréchal Foch","HouseNumber":"53","PostalCode":"76190","AdditionalData":[{"value":"France","key":"CountryName"},{"value":"Normandie","key":"StateName"},{"value":"Seine-Maritime","key":"CountyName"}]},"MapReference":{"ReferenceId":"1221784163","Spot":0.13,"SideOfStreet":"right","CountryId":"20000001","StateId":"20057204","CountyId":"20038936","CityId":"20080039","AddressId":"379358566","RoadLinkId":"539265170"}}},{"Relevance":1.0,"Distance":38.4,"MatchLevel":"houseNumber","MatchQuality":{"Country":1.0,"State":1.0,"County":1.0,"City":1.0,"Street":[1.0],"HouseNumber":1.0,"PostalCode":1.0},"MatchType":"interpolated","Location":{"LocationId":"NT_8Tengq-WX09TNjSskzVtBA_yID","LocationType":"point","DisplayPosition":{"Latitude":49.61789,"Longitude":0.74347},"MapView":{"TopLeft":{"Latitude":49.6190142,"Longitude":0.7417349},"BottomRight":{"Latitude":49.6167658,"Longitude":0.7452051}},"Address":{"Label":"22 Rue des Magasins, 76190 Yvetot, France","Country":"FRA","State":"Normandie","County":"Seine-Maritime","City":"Yvetot","Street":"Rue des Magasins","HouseNumber":"22","PostalCode":"76190","AdditionalData":[{"value":"France","key":"CountryName"},{"value":"Normandie","key":"StateName"},{"value":"Seine-Maritime","key":"CountyName"}]},"MapReference":{"ReferenceId":"545577388","Spot":0.64,"SideOfStreet":"right","CountryId":"20000001","StateId":"20057204","CountyId":"20038936","CityId":"20080039","AddressId":"316758914","RoadLinkId":"47228457"}}},{"Relevance":1.0,"Distance":41.0,"MatchLevel":"houseNumber","MatchQuality":{"Country":1.0,"State":1.0,"County":1.0,"City":1.0,"Street":[1.0],"HouseNumber":1.0,"PostalCode":1.0},"MatchType":"interpolated","Location":{"LocationId":"NT_9.mW5TOBJD3wwzR0ZMAC1D_xYD","LocationType":"point","DisplayPosition":{"Latitude":49.61819,"Longitude":0.74403},"MapView":{"TopLeft":{"Latitude":49.6193142,"Longitude":0.7422949},"BottomRight":{"Latitude":49.6170658,"Longitude":0.7457651}},"Address":{"Label":"16 Avenue du Maréchal Foch, 76190 Yvetot, France","Country":"FRA","State":"Normandie","County":"Seine-Maritime","City":"Yvetot","Street":"Avenue du Maréchal Foch","HouseNumber":"16","PostalCode":"76190","AdditionalData":[{"value":"France","key":"CountryName"},{"value":"Normandie","key":"StateName"},{"value":"Seine-Maritime","key":"CountyName"}]},"MapReference":{"ReferenceId":"1221762332","Spot":0.12,"SideOfStreet":"left","CountryId":"20000001","StateId":"20057204","CountyId":"20038936","CityId":"20080039","AddressId":"379358565","RoadLinkId":"539240007"}}},{"Relevance":1.0,"Distance":72.6,"MatchLevel":"houseNumber","MatchQuality":{"Country":1.0,"State":1.0,"County":1.0,"City":1.0,"Street":[1.0],"HouseNumber":1.0,"PostalCode":1.0},"MatchType":"interpolated","Location":{"LocationId":"NT_9.mW5TOBJD3wwzR0ZMAC1D_xgD","LocationType":"point","DisplayPosition":{"Latitude":49.6181,"Longitude":0.74246},"MapView":{"TopLeft":{"Latitude":49.6192242,"Longitude":0.7407249},"BottomRight":{"Latitude":49.6169758,"Longitude":0.7441951}},"Address":{"Label":"18 Avenue du Maréchal Foch, 76190 Yvetot, France","Country":"FRA","State":"Normandie","County":"Seine-Maritime","City":"Yvetot","Street":"Avenue du Maréchal Foch","HouseNumber":"18","PostalCode":"76190","AdditionalData":[{"value":"France","key":"CountryName"},{"value":"Normandie","key":"StateName"},{"value":"Seine-Maritime","key":"CountyName"}]},"MapReference":{"ReferenceId":"1221762341","Spot":0.21,"SideOfStreet":"left","CountryId":"20000001","StateId":"20057204","CountyId":"20038936","CityId":"20080039","AddressId":"379361243","RoadLinkId":"539240030"}}},{"Relevance":1.0,"Distance":85.9,"MatchLevel":"houseNumber","MatchQuality":{"Country":1.0,"State":1.0,"County":1.0,"City":1.0,"Street":[1.0],"HouseNumber":1.0,"PostalCode":1.0},"MatchType":"interpolated","Location":{"LocationId":"NT_9.mW5TOBJD3wwzR0ZMAC1D_1cD","LocationType":"point","DisplayPosition":{"Latitude":49.6181,"Longitude":0.74229},"MapView":{"TopLeft":{"Latitude":49.6192242,"Longitude":0.7405549},"BottomRight":{"Latitude":49.6169758,"Longitude":0.7440251}},"Address":{"Label":"57 Avenue du Maréchal Foch, 76190 Yvetot, France","Country":"FRA","State":"Normandie","County":"Seine-Maritime","City":"Yvetot","Street":"Avenue du Maréchal Foch","HouseNumber":"57","PostalCode":"76190","AdditionalData":[{"value":"France","key":"CountryName"},{"value":"Normandie","key":"StateName"},{"value":"Seine-Maritime","key":"CountyName"}]},"MapReference":{"ReferenceId":"810529987","Spot":0.93,"SideOfStreet":"right","CountryId":"20000001","StateId":"20057204","CountyId":"20038936","CityId":"20080039","AddressId":"316692533","RoadLinkId":"197824610"}}},{"Relevance":1.0,"Distance":98.6,"MatchLevel":"street","MatchQuality":{"Country":1.0,"State":1.0,"County":1.0,"City":1.0,"Street":[1.0],"PostalCode":1.0},"Location":{"LocationId":"NT_9.mW5TOBJD3wwzR0ZMAC1D_l_545575920_L","LocationType":"point","DisplayPosition":{"Latitude":49.61824,"Longitude":0.74483},"MapView":{"TopLeft":{"Latitude":49.61825,"Longitude":0.74483},"BottomRight":{"Latitude":49.61824,"Longitude":0.74505}},"Address":{"Label":"Avenue du Maréchal Foch, 76190 Yvetot, France","Country":"FRA","State":"Normandie","County":"Seine-Maritime","City":"Yvetot","Street":"Avenue du Maréchal Foch","PostalCode":"76190","AdditionalData":[{"value":"France","key":"CountryName"},{"value":"Normandie","key":"StateName"},{"value":"Seine-Maritime","key":"CountyName"}]},"MapReference":{"ReferenceId":"545575920","Spot":0.0,"SideOfStreet":"left","CountryId":"20000001","StateId":"20057204","CountyId":"20038936","CityId":"20080039"}}}]}]}}