{"Response":{"MetaInfo":{"Timestamp":"2020-03-28T10:25:17.939+0000","NextPageInformation":"2"},"View":[{"_type":"SearchResultsViewType","ViewId":0,"Result":[{"Relevance":1.0,"Distance":0.0,"Direction":0.0,"MatchLevel":"district","MatchQuality":{"Country":1.0,"State":1.0,"County":1.0,"City":1.0,"District":1.0,"PostalCode":1.0},"Location":{"LocationId":"NT_mYIXrDVgx3x0w.6t2QLlDD","LocationType":"point","DisplayPosition":{"Latitude":52.3164817,"Longitude":7.8841276},"MapView":{"TopLeft":{"Latitude":52.32153,"Longitude":7.86501},"BottomRight":{"Latitude":52.30667,"Longitude":7.90358}},"Address":{"Label":"Westerkappeln, Nordrhein-Westfalen, Deutschland","Country":"DEU","State":"Nordrhein-Westfalen","County":"Steinfurt","City":"Westerkappeln","District":"Westerkappeln","PostalCode":"49492","AdditionalData":[{"value":"Deutschland","key":"CountryName"},{"value":"Nordrhein-Westfalen","key":"StateName"},{"value":"Steinfurt","key":"CountyName"}]},"MapReference":{"ReferenceId":"75392374","SideOfStreet":"neither","CountryId":"20147700","StateId":"20157369","CountyId":"20159347","CityId":"20159451","DistrictId":"20159454"}}},{"Relevance":1.0,"Distance":24.7,"MatchLevel":"houseNumber","MatchQuality":{"Country":1.0,"State":1.0,"County":1.0,"City":1.0,"District":1.0,"Street":[1.0],"HouseNumber":1.0,"PostalCode":1.0},"MatchType":"interpolated","Location":{"LocationId":"NT_FnCePSBfScNBS0PmxiRdXD_xA","LocationType":"point","DisplayPosition":{"Latitude":52.31626,"Longitude":7.88398},"MapView":{"TopLeft":{"Latitude":52.3173842,"Longitude":7.8821411},"BottomRight":{"Latitude":52.3151358,"Longitude":7.8858189}},"Address":{"Label":"Wilkenkampstraße 1, 49492 Westerkappeln, Deutschland","Country":"DEU","State":"Nordrhein-Westfalen","County":"Steinfurt","City":"Westerkappeln","District":"Westerkappeln","Street":"Wilkenkampstraße","HouseNumber":"1","PostalCode":"49492","AdditionalData":[{"value":"Deutschland","key":"CountryName"},{"value":"Nordrhein-Westfalen","key":"StateName"},{"value":"Steinfurt","key":"CountyName"}]},"MapReference":{"ReferenceId":"69250581","Spot":0.69,"SideOfStreet":"right","CountryId":"20147700","StateId":"20157369","CountyId":"20159347","CityId":"20159451","DistrictId":"20159454","AddressId":"194745510","RoadLinkId":"35263029"}}},{"Relevance":1.0,"Distance":30.8,"MatchLevel":"houseNumber","MatchQuality":{"Country":1.0,"State":1.0,"County":1.0,"City":1.0,"District":1.0,"Street":[1.0],"HouseNumber":1.0,"PostalCode":1.0},"MatchType":"interpolated","Location":{"LocationId":"NT_slsucbR8kseRAbh7zkZfyD_yID","LocationType":"point","DisplayPosition":{"Latitude":52.31653,"Longitude":7.88365},"MapView":{"TopLeft":{"Latitude":52.3176542,"Longitude":7.881811},"BottomRight":{"Latitude":52.3154058,"Longitude":7.885489}},"Address":{"Label":"Hanfriedenstraße 22, 49492 Westerkappeln, Deutschland","Country":"DEU","State":"Nordrhein-Westfalen","County":"Steinfurt","City":"Westerkappeln","District":"Westerkappeln","Street":"Hanfriedenstraße","HouseNumber":"22","PostalCode":"49492","AdditionalData":[{"value":"Deutschland","key":"CountryName"},{"value":"Nordrhein-Westfalen","key":"StateName"},{"value":"Steinfurt","key":"CountyName"}]},"MapReference":{"ReferenceId":"69250561","Spot":0.76,"SideOfStreet":"right","CountryId":"20147700","StateId":"20157369","CountyId":"20159347","CityId":"20159451","DistrictId":"20159454","AddressId":"194099689","RoadLinkId":"35507332"}}},{"Relevance":1.0,"Distance":31.5,"MatchLevel":"houseNumber","MatchQuality":{"Country":1.0,"State":1.0,"County":1.0,"City":1.0,"District":1.0,"Street":[1.0],"HouseNumber":1.0,"PostalCode":1.0},"MatchType":"interpolated","Location":{"LocationId":"NT_slsucbR8kseRAbh7zkZfyD_yQD","LocationType":"point","DisplayPosition":{"Latitude":52.31665,"Longitude":7.8845},"MapView":{"TopLeft":{"Latitude":52.3177742,"Longitude":7.882661},"BottomRight":{"Latitude":52.3155258,"Longitude":7.886339}},"Address":{"Label":"Hanfriedenstraße 24, 49492 Westerkappeln, Deutschland","Country":"DEU","State":"Nordrhein-Westfalen","County":"Steinfurt","City":"Westerkappeln","District":"Westerkappeln","Street":"Hanfriedenstraße","HouseNumber":"24","PostalCode":"49492","AdditionalData":[{"value":"Deutschland","key":"CountryName"},{"value":"Nordrhein-Westfalen","key":"StateName"},{"value":"Steinfurt","key":"CountyName"}]},"MapReference":{"ReferenceId":"76198079","Spot":0.58,"SideOfStreet":"right","CountryId":"20147700","StateId":"20157369","CountyId":"20159347","CityId":"20159451","DistrictId":"20159454","AddressId":"194007417","RoadLinkId":"35381934"}}},{"Relevance":1.0,"Distance":39.1,"MatchLevel":"houseNumber","MatchQuality":{"Country":1.0,"State":1.0,"County":1.0,"City":1.0,"District":1.0,"Street":[1.0],"HouseNumber":1.0,"PostalCode":1.0},"MatchType":"interpolated","Location":{"LocationId":"NT_ACEBoPndGfO-vWnx-6ZYzB_2A","LocationType":"point","DisplayPosition":{"Latitude":52.31619,"Longitude":7.88496},"MapView":{"TopLeft":{"Latitude":52.3173142,"Longitude":7.8831211},"BottomRight":{"Latitude":52.3150658,"Longitude":7.8867989}},"Address":{"Label":"Am Stadion 6, 49492 Westerkappeln, Deutschland","Country":"DEU","State":"Nordrhein-Westfalen","County":"Steinfurt","City":"Westerkappeln","District":"Westerkappeln","Street":"Am Stadion","HouseNumber":"6","PostalCode":"49492","AdditionalData":[{"value":"Deutschland","key":"CountryName"},{"value":"Nordrhein-Westfalen","key":"StateName"},{"value":"Steinfurt","key":"CountyName"}]},"MapReference":{"ReferenceId":"69250548","Spot":0.3,"SideOfStreet":"left","CountryId":"20147700","StateId":"20157369","CountyId":"20159347","CityId":"20159451","DistrictId":"20159454","AddressId":"194969010","RoadLinkId":"35656958"}}},{"Relevance":1.0,"Distance":57.4,"MatchLevel":"houseNumber","MatchQuality":{"Country":1.0,"State":1.0,"County":1.0,"City":1.0,"District":1.0,"Street":[1.0],"HouseNumber":1.0,"PostalCode":1.0},"MatchType":"interpolated","Location":{"LocationId":"NT_slsucbR8kseRAbh7zkZfyD_xA","LocationType":"point","DisplayPosition":{"Latitude":52.31669,"Longitude":7.8849},"MapView":{"TopLeft":{"Latitude":52.3178142,"Longitude":7.883061},"BottomRight":{"Latitude":52.3155658,"Longitude":7.886739}},"Address":{"Label":"Hanfriedenstraße 1, 49492 Westerkappeln, Deutschland","Country":"DEU","State":"Nordrhein-Westfalen","County":"Steinfurt","City":"Westerkappeln","District":"Westerkappeln","Street":"Hanfriedenstraße","HouseNumber":"1","PostalCode":"49492","AdditionalData":[{"value":"Deutschland","key":"CountryName"},{"value":"Nordrhein-Westfalen","key":"StateName"},{"value":"Steinfurt","key":"CountyName"}]},"MapReference":{"ReferenceId":"76198080","Spot":0.1,"SideOfStreet":"right","CountryId":"20147700","StateId":"20157369","CountyId":"20159347","CityId":"20159451","DistrictId":"20159454","AddressId":"196645730","RoadLinkId":"35500406"}}},{"Relevance":1.0,"Distance":82.7,"MatchLevel":"houseNumber","MatchQuality":{"Country":1.0,"State":1.0,"County":1.0,"City":1.0,"District":1.0,"Street":[1.0],"HouseNumber":1.0,"PostalCode":1.0},"MatchType":"interpolated","Location":{"LocationId":"NT_slsucbR8kseRAbh7zkZfyD_zATQ","LocationType":"point","DisplayPosition":{"Latitude":52.31672,"Longitude":7.88528},"MapView":{"TopLeft":{"Latitude":52.3178442,"Longitude":7.883441},"BottomRight":{"Latitude":52.3155958,"Longitude":7.887119}},"Address":{"Label":"Hanfriedenstraße 30A, 49492 Westerkappeln, Deutschland","Country":"DEU","State":"Nordrhein-Westfalen","County":"Steinfurt","City":"Westerkappeln","District":"Westerkappeln","Street":"Hanfriedenstraße","HouseNumber":"30A","PostalCode":"49492","AdditionalData":[{"value":"Deutschland","key":"CountryName"},{"value":"Nordrhein-Westfalen","key":"StateName"},{"value":"Steinfurt","key":"CountyName"}]},"MapReference":{"ReferenceId":"69250541","Spot":0.19,"SideOfStreet":"right","CountryId":"20147700","StateId":"20157369","CountyId":"20159347","CityId":"20159451","DistrictId":"20159454","AddressId":"195839106","RoadLinkId":"35476060"}}},{"Relevance":1.0,"Distance":89.8,"MatchLevel":"houseNumber","MatchQuality":{"Country":1.0,"State":1.0,"County":1.0,"City":1.0,"District":1.0,"Street":[1.0],"HouseNumber":1.0,"PostalCode":1.0},"MatchType":"interpolated","Location":{"LocationId":"NT_vF4t-fpaOWIHlRKz18wrOD_0A","LocationType":"point","DisplayPosition":{"Latitude":52.31679,"Longitude":7.88271},"MapView":{"TopLeft":{"Latitude":52.3179142,"Longitude":7.880871},"BottomRight":{"Latitude":52.3156658,"Longitude":7.884549}},"Address":{"Label":"Rüskenkampstraße 4, 49492 Westerkappeln, Deutschland","Country":"DEU","State":"Nordrhein-Westfalen","County":"Steinfurt","City":"Westerkappeln","District":"Westerkappeln","Street":"Rüskenkampstraße","HouseNumber":"4","PostalCode":"49492","AdditionalData":[{"value":"Deutschland","key":"CountryName"},{"value":"Nordrhein-Westfalen","key":"StateName"},{"value":"Steinfurt","key":"CountyName"}]},"MapReference":{"ReferenceId":"69250564","Spot":0.49,"SideOfStreet":"right","CountryId":"20147700","StateId":"20157369","CountyId":"20159347","CityId":"20159451","DistrictId":"20159454","AddressId":"192561800","RoadLinkId":"35202753"}}},{"Relevance":1.0,"Distance":115.7,"MatchLevel":"houseNumber","MatchQuality":{"Country":1.0,"State":1.0,"County":1.0,"City":1.0,"District":1.0,"Street":[1.0],"HouseNumber":1.0,"PostalCode":1.0},"MatchType":"interpolated","Location":{"LocationId":"NT_FnCePSBfScNBS0PmxiRdXD_3A","LocationType":"point","DisplayPosition":{"Latitude":52.31545,"Longitude":7.88391},"MapView":{"TopLeft":{"Latitude":52.3165742,"Longitude":7.8820711},"BottomRight":{"Latitude":52.3143258,"Longitude":7.8857489}},"Address":{"Label":"Wilkenkampstraße 7, 49492 Westerkappeln, Deutschland","Country":"DEU","State":"Nordrhein-Westfalen","County":"Steinfurt","City":"Westerkappeln","District":"Westerkappeln","Street":"Wilkenkampstraße","HouseNumber":"7","PostalCode":"49492","AdditionalData":[{"value":"Deutschland","key":"CountryName"},{"value":"Nordrhein-Westfalen","key":"StateName"},{"value":"Steinfurt","key":"CountyName"}]},"MapReference":{"ReferenceId":"69250580","Spot":0.84,"SideOfStreet":"right","CountryId":"20147700","StateId":"20157369","CountyId":"20159347","CityId":"20159451","DistrictId":"20159454","AddressId":"192668552","RoadLinkId":"35584240"}}},{"Relevance":1.0,"Distance":119.4,"MatchLevel":"houseNumber","MatchQuality":{"Country":1.0,"State":1.0,"County":1.0,"City":1.0,"District":1.0,"Street":[1.0],"HouseNumber":1.0,"PostalCode":1.0},"MatchType":"interpolated","Location":{"LocationId":"NT_vF4t-fpaOWIHlRKz18wrOD_xAD","LocationType":"point","DisplayPosition":{"Latitude":52.31731,"Longitude":7.88281},"MapView":{"TopLeft":{"Latitude":52.3184342,"Longitude":7.880971},"BottomRight":{"Latitude":52.3161858,"Longitude":7.884649}},"Address":{"Label":"Rüskenkampstraße 10, 49492 Westerkappeln, Deutschland","Country":"DEU","State":"Nordrhein-Westfalen","County":"Steinfurt","City":"Westerkappeln","District":"Westerkappeln","Street":"Rüskenkampstraße","HouseNumber":"10","PostalCode":"49492","AdditionalData":[{"value":"Deutschland","key":"CountryName"},{"value":"Nordrhein-Westfalen","key":"StateName"},{"value":"Steinfurt","key":"CountyName"}]},"MapReference":{"ReferenceId":"69250554","Spot":0.09,"SideOfStreet":"right","CountryId":"20147700","StateId":"20157369","CountyId":"20159347","CityId":"20159451","DistrictId":"20159454","AddressId":"195015996","RoadLinkId":"35330292"}}}]}]}}